<?xml version="1.0" encoding="UTF-8"?>
<YFS_SOURCING_RULE_DTLList TableName="YFS_SOURCING_RULE_DTL" TotalNumberOfRecords="24">
<SourcingRuleDetail Createprogid="XMLMigrator"
    Createts="2019-05-28T22:11:39-04:00" Createuserid="SYSTEM"
    DistributionRuleId="Aurora-Corp_DG2" FromNodeKey="" Lockid="0"
    Modifyprogid="XMLMigrator" Modifyts="2019-05-28T22:11:39-04:00"
    Modifyuserid="SYSTEM" ProcureToShipAllowed="" SeqNo="2"
    SourcingRuleDetailKey="2001098893762"
    SourcingRuleHeaderKey="Aurora-Corp_SRH4" SourcingTemplate=""
    SubstitutionAllowed="" TemplateType="Distribution_Group" WorkOrderCreationAllowed=""/>
<SourcingRuleDetail Createprogid="XMLMigrator"
    Createts="2019-05-28T22:11:39-04:00" Createuserid="SYSTEM"
    DistributionRuleId="Aurora-Corp_DG1" FromNodeKey="" Lockid="0"
    Modifyprogid="XMLMigrator" Modifyts="2019-05-28T22:11:39-04:00"
    Modifyuserid="SYSTEM" ProcureToShipAllowed="" SeqNo="1"
    SourcingRuleDetailKey="2001098893763"
    SourcingRuleHeaderKey="Aurora-Corp_SRH4" SourcingTemplate=""
    SubstitutionAllowed="" TemplateType="Distribution_Group" WorkOrderCreationAllowed=""/>
<SourcingRuleDetail Createprogid="XMLMigrator"
    Createts="2019-05-28T22:11:39-04:00" Createuserid="SYSTEM"
    DistributionRuleId="Aurora-Corp_DG2" FromNodeKey="" Lockid="0"
    Modifyprogid="XMLMigrator" Modifyts="2019-05-28T22:11:39-04:00"
    Modifyuserid="SYSTEM" ProcureToShipAllowed="" SeqNo="1"
    SourcingRuleDetailKey="2001098894724"
    SourcingRuleHeaderKey="Aurora-Corp_SRH3" SourcingTemplate=""
    SubstitutionAllowed="" TemplateType="Distribution_Group" WorkOrderCreationAllowed=""/>
<SourcingRuleDetail Createprogid="XMLMigrator"
    Createts="2019-05-28T22:11:39-04:00" Createuserid="SYSTEM"
    DistributionRuleId="Aurora-Corp_DG1" FromNodeKey="" Lockid="0"
    Modifyprogid="XMLMigrator" Modifyts="2019-05-28T22:11:39-04:00"
    Modifyuserid="SYSTEM" ProcureToShipAllowed="" SeqNo="2"
    SourcingRuleDetailKey="2001098895684"
    SourcingRuleHeaderKey="Aurora-Corp_SRH2" SourcingTemplate=""
    SubstitutionAllowed="" TemplateType="Distribution_Group" WorkOrderCreationAllowed=""/>
<SourcingRuleDetail Createprogid="XMLMigrator"
    Createts="2019-05-28T22:11:39-04:00" Createuserid="SYSTEM"
    DistributionRuleId="Aurora-Corp_DG2" FromNodeKey="" Lockid="0"
    Modifyprogid="XMLMigrator" Modifyts="2019-05-28T22:11:39-04:00"
    Modifyuserid="SYSTEM" ProcureToShipAllowed="" SeqNo="1"
    SourcingRuleDetailKey="2001098895685"
    SourcingRuleHeaderKey="Aurora-Corp_SRH2" SourcingTemplate=""
    SubstitutionAllowed="" TemplateType="Distribution_Group" WorkOrderCreationAllowed=""/>
<SourcingRuleDetail Createprogid="XMLMigrator"
    Createts="2019-05-28T22:11:39-04:00" Createuserid="SYSTEM"
    DistributionRuleId="Aurora-Corp_DG2" FromNodeKey="" Lockid="0"
    Modifyprogid="XMLMigrator" Modifyts="2019-05-28T22:11:39-04:00"
    Modifyuserid="SYSTEM" ProcureToShipAllowed="" SeqNo="1"
    SourcingRuleDetailKey="2001098896646"
    SourcingRuleHeaderKey="Aurora-Corp_SRH1" SourcingTemplate=""
    SubstitutionAllowed="" TemplateType="Distribution_Group" WorkOrderCreationAllowed=""/>
<SourcingRuleDetail Createprogid="XMLMigrator"
    Createts="2019-05-28T22:12:03-04:00" Createuserid="SYSTEM"
    DistributionRuleId="Aurora_DG2" FromNodeKey="" Lockid="0"
    Modifyprogid="XMLMigrator" Modifyts="2019-05-28T22:12:03-04:00"
    Modifyuserid="SYSTEM" ProcureToShipAllowed="" SeqNo="2"
    SourcingRuleDetailKey="2001261574773"
    SourcingRuleHeaderKey="Aurora_SRH4" SourcingTemplate=""
    SubstitutionAllowed="" TemplateType="Distribution_Group" WorkOrderCreationAllowed=""/>
<SourcingRuleDetail Createprogid="XMLMigrator"
    Createts="2019-05-28T22:12:03-04:00" Createuserid="SYSTEM"
    DistributionRuleId="Aurora_DG1" FromNodeKey="" Lockid="0"
    Modifyprogid="XMLMigrator" Modifyts="2019-05-28T22:12:03-04:00"
    Modifyuserid="SYSTEM" ProcureToShipAllowed="" SeqNo="1"
    SourcingRuleDetailKey="2001261574774"
    SourcingRuleHeaderKey="Aurora_SRH4" SourcingTemplate=""
    SubstitutionAllowed="" TemplateType="Distribution_Group" WorkOrderCreationAllowed=""/>
<SourcingRuleDetail Createprogid="XMLMigrator"
    Createts="2019-05-28T22:12:03-04:00" Createuserid="SYSTEM"
    DistributionRuleId="Aurora_DG2" FromNodeKey="" Lockid="0"
    Modifyprogid="XMLMigrator" Modifyts="2019-05-28T22:12:03-04:00"
    Modifyuserid="SYSTEM" ProcureToShipAllowed="" SeqNo="1"
    SourcingRuleDetailKey="2001261575735"
    SourcingRuleHeaderKey="Aurora_SRH3" SourcingTemplate=""
    SubstitutionAllowed="" TemplateType="Distribution_Group" WorkOrderCreationAllowed=""/>
<SourcingRuleDetail Createprogid="XMLMigrator"
    Createts="2019-05-28T22:12:03-04:00" Createuserid="SYSTEM"
    DistributionRuleId="Aurora_DG1" FromNodeKey="" Lockid="0"
    Modifyprogid="XMLMigrator" Modifyts="2019-05-28T22:12:03-04:00"
    Modifyuserid="SYSTEM" ProcureToShipAllowed="" SeqNo="2"
    SourcingRuleDetailKey="2001261576695"
    SourcingRuleHeaderKey="Aurora_SRH2" SourcingTemplate=""
    SubstitutionAllowed="" TemplateType="Distribution_Group" WorkOrderCreationAllowed=""/>
<SourcingRuleDetail Createprogid="XMLMigrator"
    Createts="2019-05-28T22:12:03-04:00" Createuserid="SYSTEM"
    DistributionRuleId="Aurora_DG2" FromNodeKey="" Lockid="0"
    Modifyprogid="XMLMigrator" Modifyts="2019-05-28T22:12:03-04:00"
    Modifyuserid="SYSTEM" ProcureToShipAllowed="" SeqNo="1"
    SourcingRuleDetailKey="2001261576696"
    SourcingRuleHeaderKey="Aurora_SRH2" SourcingTemplate=""
    SubstitutionAllowed="" TemplateType="Distribution_Group" WorkOrderCreationAllowed=""/>
<SourcingRuleDetail Createprogid="XMLMigrator"
    Createts="2019-05-28T22:12:03-04:00" Createuserid="SYSTEM"
    DistributionRuleId="Aurora_DG2" FromNodeKey="" Lockid="0"
    Modifyprogid="XMLMigrator" Modifyts="2019-05-28T22:12:03-04:00"
    Modifyuserid="SYSTEM" ProcureToShipAllowed="" SeqNo="1"
    SourcingRuleDetailKey="2001261577657"
    SourcingRuleHeaderKey="Aurora_SRH1" SourcingTemplate=""
    SubstitutionAllowed="" TemplateType="Distribution_Group" WorkOrderCreationAllowed=""/>
<SourcingRuleDetail Createprogid="XMLMigrator"
    Createts="2019-05-28T22:15:28-04:00" Createuserid="SYSTEM"
    DistributionRuleId="" FromNodeKey="Auro_Store_3" Lockid="0"
    Modifyprogid="XMLMigrator" Modifyts="2019-05-28T22:15:28-04:00"
    Modifyuserid="SYSTEM" ProcureToShipAllowed="" SeqNo="3"
    SourcingRuleDetailKey="200445870340"
    SourcingRuleHeaderKey="Aurora_SRPS1" SourcingTemplate=""
    SubstitutionAllowed="" TemplateType="Specific_Node" WorkOrderCreationAllowed=""/>
<SourcingRuleDetail Createprogid="XMLMigrator"
    Createts="2019-05-28T22:15:28-04:00" Createuserid="SYSTEM"
    DistributionRuleId="" FromNodeKey="Auro_Store_2" Lockid="0"
    Modifyprogid="XMLMigrator" Modifyts="2019-05-28T22:15:28-04:00"
    Modifyuserid="SYSTEM" ProcureToShipAllowed="" SeqNo="2"
    SourcingRuleDetailKey="200445870341"
    SourcingRuleHeaderKey="Aurora_SRPS1" SourcingTemplate=""
    SubstitutionAllowed="" TemplateType="Specific_Node" WorkOrderCreationAllowed=""/>
<SourcingRuleDetail Createprogid="XMLMigrator"
    Createts="2019-05-28T22:12:04-04:00" Createuserid="SYSTEM"
    DistributionRuleId="Aurora_PS_DG1" FromNodeKey="" Lockid="0"
    Modifyprogid="XMLMigrator" Modifyts="2019-05-28T22:12:04-04:00"
    Modifyuserid="SYSTEM" ProcureToShipAllowed="" SeqNo="1"
    SourcingRuleDetailKey="200445870342"
    SourcingRuleHeaderKey="Aurora_SRPS1" SourcingTemplate=""
    SubstitutionAllowed="" TemplateType="Distribution_Group" WorkOrderCreationAllowed=""/>
<SourcingRuleDetail Createprogid="XMLMigrator"
    Createts="2019-05-28T22:15:28-04:00" Createuserid="SYSTEM"
    DistributionRuleId="" FromNodeKey="Auro_Store_3" Lockid="0"
    Modifyprogid="XMLMigrator" Modifyts="2019-05-28T22:15:28-04:00"
    Modifyuserid="SYSTEM" ProcureToShipAllowed="" SeqNo="3"
    SourcingRuleDetailKey="200456952592"
    SourcingRuleHeaderKey="Aurora_SRDS1" SourcingTemplate=""
    SubstitutionAllowed="" TemplateType="Specific_Node" WorkOrderCreationAllowed=""/>
<SourcingRuleDetail Createprogid="XMLMigrator"
    Createts="2019-05-28T22:15:28-04:00" Createuserid="SYSTEM"
    DistributionRuleId="" FromNodeKey="Auro_Store_2" Lockid="0"
    Modifyprogid="XMLMigrator" Modifyts="2019-05-28T22:15:28-04:00"
    Modifyuserid="SYSTEM" ProcureToShipAllowed="" SeqNo="2"
    SourcingRuleDetailKey="200456952593"
    SourcingRuleHeaderKey="Aurora_SRDS1" SourcingTemplate=""
    SubstitutionAllowed="" TemplateType="Specific_Node" WorkOrderCreationAllowed=""/>
<SourcingRuleDetail Createprogid="XMLMigrator"
    Createts="2019-05-28T22:12:03-04:00" Createuserid="SYSTEM"
    DistributionRuleId="Aurora_DEL_DG1" FromNodeKey="" Lockid="0"
    Modifyprogid="XMLMigrator" Modifyts="2019-05-28T22:12:03-04:00"
    Modifyuserid="SYSTEM" ProcureToShipAllowed="" SeqNo="1"
    SourcingRuleDetailKey="200456952594"
    SourcingRuleHeaderKey="Aurora_SRDS1" SourcingTemplate=""
    SubstitutionAllowed="" TemplateType="Distribution_Group" WorkOrderCreationAllowed=""/>
<SourcingRuleDetail Createprogid="XMLMigrator"
    Createts="2019-05-28T22:11:39-04:00" Createuserid="SYSTEM"
    DistributionRuleId="Aurora-Corp_DEL_DG1" FromNodeKey="" Lockid="0"
    Modifyprogid="XMLMigrator" Modifyts="2019-05-28T22:11:39-04:00"
    Modifyuserid="SYSTEM" ProcureToShipAllowed="" SeqNo="1"
    SourcingRuleDetailKey="20291191451"
    SourcingRuleHeaderKey="Aurora-Corp_SRDS1" SourcingTemplate=""
    SubstitutionAllowed="" TemplateType="Distribution_Group" WorkOrderCreationAllowed=""/>
<SourcingRuleDetail Createprogid="XMLMigrator"
    Createts="2019-05-28T22:15:11-04:00" Createuserid="SYSTEM"
    DistributionRuleId="" FromNodeKey="Auro_Store_2" Lockid="0"
    Modifyprogid="XMLMigrator" Modifyts="2019-05-28T22:15:11-04:00"
    Modifyuserid="SYSTEM" ProcureToShipAllowed="" SeqNo="2"
    SourcingRuleDetailKey="20291191452"
    SourcingRuleHeaderKey="Aurora-Corp_SRDS1" SourcingTemplate=""
    SubstitutionAllowed="" TemplateType="Specific_Node" WorkOrderCreationAllowed=""/>
<SourcingRuleDetail Createprogid="XMLMigrator"
    Createts="2019-05-28T22:15:11-04:00" Createuserid="SYSTEM"
    DistributionRuleId="" FromNodeKey="Auro_Store_3" Lockid="0"
    Modifyprogid="XMLMigrator" Modifyts="2019-05-28T22:15:11-04:00"
    Modifyuserid="SYSTEM" ProcureToShipAllowed="" SeqNo="3"
    SourcingRuleDetailKey="20291191453"
    SourcingRuleHeaderKey="Aurora-Corp_SRDS1" SourcingTemplate=""
    SubstitutionAllowed="" TemplateType="Specific_Node" WorkOrderCreationAllowed=""/>
<SourcingRuleDetail Createprogid="XMLMigrator"
    Createts="2019-05-28T22:11:39-04:00" Createuserid="SYSTEM"
    DistributionRuleId="Aurora-Corp_PS_DG1" FromNodeKey="" Lockid="0"
    Modifyprogid="XMLMigrator" Modifyts="2019-05-28T22:11:39-04:00"
    Modifyuserid="SYSTEM" ProcureToShipAllowed="" SeqNo="1"
    SourcingRuleDetailKey="20302273703"
    SourcingRuleHeaderKey="Aurora-Corp_SRPS1" SourcingTemplate=""
    SubstitutionAllowed="" TemplateType="Distribution_Group" WorkOrderCreationAllowed=""/>
<SourcingRuleDetail Createprogid="XMLMigrator"
    Createts="2019-05-28T22:15:11-04:00" Createuserid="SYSTEM"
    DistributionRuleId="" FromNodeKey="Auro_Store_2" Lockid="0"
    Modifyprogid="XMLMigrator" Modifyts="2019-05-28T22:15:11-04:00"
    Modifyuserid="SYSTEM" ProcureToShipAllowed="" SeqNo="2"
    SourcingRuleDetailKey="20302273704"
    SourcingRuleHeaderKey="Aurora-Corp_SRPS1" SourcingTemplate=""
    SubstitutionAllowed="" TemplateType="Specific_Node" WorkOrderCreationAllowed=""/>
<SourcingRuleDetail Createprogid="XMLMigrator"
    Createts="2019-05-28T22:15:11-04:00" Createuserid="SYSTEM"
    DistributionRuleId="" FromNodeKey="Auro_Store_3" Lockid="0"
    Modifyprogid="XMLMigrator" Modifyts="2019-05-28T22:15:11-04:00"
    Modifyuserid="SYSTEM" ProcureToShipAllowed="" SeqNo="3"
    SourcingRuleDetailKey="20302273705"
    SourcingRuleHeaderKey="Aurora-Corp_SRPS1" SourcingTemplate=""
    SubstitutionAllowed="" TemplateType="Specific_Node" WorkOrderCreationAllowed=""/>
</YFS_SOURCING_RULE_DTLList>