<?xml version="1.0" encoding="UTF-8"?>
<YFS_CHARGE_CATEGORYList TableName="YFS_CHARGE_CATEGORY" TotalNumberOfRecords="77">
<ChargeCategory ChargeCategory="Discount"
    ChargeCategoryKey="2001212565621" ConsiderForProfitMargin="Y"
    Createprogid="XMLMigrator" Createts="2019-05-28T22:11:34-04:00"
    Createuserid="SYSTEM" Description="Discount" DocumentType="0001"
    IsBillable="Y" IsDiscount="Y" IsRefundable="Y" Lockid="0"
    Modifyprogid="XMLMigrator" Modifyts="2019-05-28T22:11:34-04:00"
    Modifyuserid="SYSTEM" OrganizationCode="Aurora-Corp"/>
<ChargeCategory ChargeCategory="Coupon"
    ChargeCategoryKey="2001244388112" ConsiderForProfitMargin="Y"
    Createprogid="XMLMigrator" Createts="2019-05-28T22:11:34-04:00"
    Createuserid="SYSTEM" Description="Coupon" DocumentType="0001"
    IsBillable="Y" IsDiscount="Y" IsRefundable="Y" Lockid="0"
    Modifyprogid="XMLMigrator" Modifyts="2019-05-28T22:11:34-04:00"
    Modifyuserid="SYSTEM" OrganizationCode="Aurora-Corp"/>
<ChargeCategory ChargeCategory="Personalization"
    ChargeCategoryKey="2001317391397" ConsiderForProfitMargin="Y"
    Createprogid="XMLMigrator" Createts="2019-05-28T22:11:59-04:00"
    Createuserid="SYSTEM" Description="Personalization"
    DocumentType="0003" IsBillable="Y" IsDiscount="N" IsRefundable="N"
    Lockid="0" Modifyprogid="XMLMigrator"
    Modifyts="2019-05-28T22:11:59-04:00" Modifyuserid="SYSTEM" OrganizationCode="Aurora"/>
<ChargeCategory ChargeCategory="ShippingDiscount"
    ChargeCategoryKey="2001403862472" ConsiderForProfitMargin="Y"
    Createprogid="XMLMigrator" Createts="2019-05-28T22:11:59-04:00"
    Createuserid="SYSTEM" Description="Shipping Discount"
    DocumentType="0003" IsBillable="Y" IsDiscount="N" IsRefundable="Y"
    Lockid="0" Modifyprogid="XMLMigrator"
    Modifyts="2019-05-28T22:11:59-04:00" Modifyuserid="SYSTEM" OrganizationCode="Aurora"/>
<ChargeCategory ChargeCategory="Handling"
    ChargeCategoryKey="2001483676881" ConsiderForProfitMargin="Y"
    Createprogid="XMLMigrator" Createts="2019-05-28T22:11:34-04:00"
    Createuserid="SYSTEM" Description="Handling" DocumentType="0001"
    IsBillable="Y" IsDiscount="N" IsRefundable="N" Lockid="0"
    Modifyprogid="XMLMigrator" Modifyts="2019-05-28T22:11:34-04:00"
    Modifyuserid="SYSTEM" OrganizationCode="Aurora-Corp"/>
<ChargeCategory ChargeCategory="ShippingDiscount"
    ChargeCategoryKey="2001515240041" ConsiderForProfitMargin="Y"
    Createprogid="XMLMigrator" Createts="2019-05-28T22:11:35-04:00"
    Createuserid="SYSTEM" Description="Shipping Discount"
    DocumentType="0003" IsBillable="Y" IsDiscount="N" IsRefundable="Y"
    Lockid="0" Modifyprogid="XMLMigrator"
    Modifyts="2019-05-28T22:11:35-04:00" Modifyuserid="SYSTEM" OrganizationCode="Aurora-Corp"/>
<ChargeCategory ChargeCategory="Coupon"
    ChargeCategoryKey="2001550966641" ConsiderForProfitMargin="Y"
    Createprogid="XMLMigrator" Createts="2019-05-28T22:11:59-04:00"
    Createuserid="SYSTEM" Description="Coupon" DocumentType="0003"
    IsBillable="Y" IsDiscount="Y" IsRefundable="Y" Lockid="0"
    Modifyprogid="XMLMigrator" Modifyts="2019-05-28T22:11:59-04:00"
    Modifyuserid="SYSTEM" OrganizationCode="Aurora"/>
<ChargeCategory ChargeCategory="Discount"
    ChargeCategoryKey="2001605592631" ConsiderForProfitMargin="Y"
    Createprogid="XMLMigrator" Createts="2019-05-28T22:11:34-04:00"
    Createuserid="SYSTEM" Description="Discount" DocumentType="0003"
    IsBillable="Y" IsDiscount="Y" IsRefundable="Y" Lockid="0"
    Modifyprogid="XMLMigrator" Modifyts="2019-05-28T22:11:34-04:00"
    Modifyuserid="SYSTEM" OrganizationCode="Aurora-Corp"/>
<ChargeCategory ChargeCategory="Discount"
    ChargeCategoryKey="2001671766935" ConsiderForProfitMargin="Y"
    Createprogid="XMLMigrator" Createts="2019-05-28T22:11:59-04:00"
    Createuserid="SYSTEM" Description="Discount" DocumentType="0015"
    IsBillable="Y" IsDiscount="Y" IsRefundable="Y" Lockid="0"
    Modifyprogid="XMLMigrator" Modifyts="2019-05-28T22:11:59-04:00"
    Modifyuserid="SYSTEM" OrganizationCode="Aurora"/>
<ChargeCategory ChargeCategory="Handling"
    ChargeCategoryKey="2001876703891" ConsiderForProfitMargin="Y"
    Createprogid="XMLMigrator" Createts="2019-05-28T22:11:34-04:00"
    Createuserid="SYSTEM" Description="Handling" DocumentType="0003"
    IsBillable="Y" IsDiscount="N" IsRefundable="N" Lockid="0"
    Modifyprogid="XMLMigrator" Modifyts="2019-05-28T22:11:34-04:00"
    Modifyuserid="SYSTEM" OrganizationCode="Aurora-Corp"/>
<ChargeCategory ChargeCategory="Handling"
    ChargeCategoryKey="2001942878195" ConsiderForProfitMargin="Y"
    Createprogid="XMLMigrator" Createts="2019-05-28T22:11:59-04:00"
    Createuserid="SYSTEM" Description="Handling" DocumentType="0015"
    IsBillable="Y" IsDiscount="N" IsRefundable="N" Lockid="0"
    Modifyprogid="XMLMigrator" Modifyts="2019-05-28T22:11:59-04:00"
    Modifyuserid="SYSTEM" OrganizationCode="Aurora"/>
<ChargeCategory ChargeCategory="Personalization"
    ChargeCategoryKey="2001966741827" ConsiderForProfitMargin="Y"
    Createprogid="XMLMigrator" Createts="2019-05-28T22:11:35-04:00"
    Createuserid="SYSTEM" Description="Personalization"
    DocumentType="0015" IsBillable="Y" IsDiscount="N" IsRefundable="N"
    Lockid="0" Modifyprogid="XMLMigrator"
    Modifyts="2019-05-28T22:11:35-04:00" Modifyuserid="SYSTEM" OrganizationCode="Aurora-Corp"/>
<ChargeCategory ChargeCategory="Shipping"
    ChargeCategoryKey="2002001985544" ConsiderForProfitMargin="Y"
    Createprogid="XMLMigrator" Createts="2019-05-28T22:11:34-04:00"
    Createuserid="SYSTEM" Description="Shipping" DocumentType="0001"
    IsBillable="Y" IsDiscount="N" IsRefundable="Y" Lockid="0"
    Modifyprogid="XMLMigrator" Modifyts="2019-05-28T22:11:34-04:00"
    Modifyuserid="SYSTEM" OrganizationCode="Aurora-Corp"/>
<ChargeCategory ChargeCategory="Coupon"
    ChargeCategoryKey="2002053734738" ConsiderForProfitMargin="Y"
    Createprogid="XMLMigrator" Createts="2019-05-28T22:11:35-04:00"
    Createuserid="SYSTEM" Description="Coupon" DocumentType="0003"
    IsBillable="Y" IsDiscount="Y" IsRefundable="Y" Lockid="0"
    Modifyprogid="XMLMigrator" Modifyts="2019-05-28T22:11:35-04:00"
    Modifyuserid="SYSTEM" OrganizationCode="Aurora-Corp"/>
<ChargeCategory ChargeCategory="Shipping"
    ChargeCategoryKey="200206122311135803" ConsiderForProfitMargin="N"
    Createprogid="XMLMigrator" Createts="2019-05-28T20:42:50-04:00"
    Createuserid="SYSTEM" Description="Shipping" DocumentType="0003"
    IsBillable="Y" IsDiscount="N" IsRefundable="Y" Lockid="0"
    Modifyprogid="XMLMigrator" Modifyts="2019-05-28T20:42:50-04:00"
    Modifyuserid="SYSTEM" OrganizationCode="DEFAULT"/>
<ChargeCategory ChargeCategory="Handling"
    ChargeCategoryKey="200206122311135805" ConsiderForProfitMargin="N"
    Createprogid="XMLMigrator" Createts="2019-05-28T20:42:50-04:00"
    Createuserid="SYSTEM" Description="Handling" DocumentType="0003"
    IsBillable="Y" IsDiscount="N" IsRefundable="Y" Lockid="0"
    Modifyprogid="XMLMigrator" Modifyts="2019-05-28T20:42:50-04:00"
    Modifyuserid="SYSTEM" OrganizationCode="DEFAULT"/>
<ChargeCategory ChargeCategory="Personalization"
    ChargeCategoryKey="200206122311135807" ConsiderForProfitMargin="N"
    Createprogid="XMLMigrator" Createts="2019-05-28T20:42:50-04:00"
    Createuserid="SYSTEM" Description="Personalization"
    DocumentType="0003" IsBillable="N" IsDiscount="N" IsRefundable="Y"
    Lockid="0" Modifyprogid="XMLMigrator"
    Modifyts="2019-05-28T20:42:50-04:00" Modifyuserid="SYSTEM" OrganizationCode="DEFAULT"/>
<ChargeCategory ChargeCategory="Fee"
    ChargeCategoryKey="200206122311135809" ConsiderForProfitMargin="N"
    Createprogid="XMLMigrator" Createts="2019-05-28T20:42:50-04:00"
    Createuserid="SYSTEM" Description="Fee" DocumentType="0003"
    IsBillable="Y" IsDiscount="N" IsRefundable="Y" Lockid="0"
    Modifyprogid="XMLMigrator" Modifyts="2019-05-28T20:42:50-04:00"
    Modifyuserid="SYSTEM" OrganizationCode="DEFAULT"/>
<ChargeCategory ChargeCategory="Discount"
    ChargeCategoryKey="200206122311135811" ConsiderForProfitMargin="N"
    Createprogid="XMLMigrator" Createts="2019-05-28T20:42:50-04:00"
    Createuserid="SYSTEM" Description="Discount" DocumentType="0003"
    IsBillable="Y" IsDiscount="Y" IsRefundable="Y" Lockid="0"
    Modifyprogid="XMLMigrator" Modifyts="2019-05-28T20:42:50-04:00"
    Modifyuserid="SYSTEM" OrganizationCode="DEFAULT"/>
<ChargeCategory ChargeCategory="Shipping"
    ChargeCategoryKey="200206122335406733" ConsiderForProfitMargin="N"
    Createprogid="XMLMigrator" Createts="2019-05-28T20:42:50-04:00"
    Createuserid="SYSTEM" Description="Shipping" DocumentType="0005"
    IsBillable="Y" IsDiscount="N" IsRefundable="Y" Lockid="0"
    Modifyprogid="XMLMigrator" Modifyts="2019-05-28T20:42:50-04:00"
    Modifyuserid="SYSTEM" OrganizationCode="DEFAULT"/>
<ChargeCategory ChargeCategory="Handling"
    ChargeCategoryKey="200206122335406735" ConsiderForProfitMargin="N"
    Createprogid="XMLMigrator" Createts="2019-05-28T20:42:50-04:00"
    Createuserid="SYSTEM" Description="Handling" DocumentType="0005"
    IsBillable="Y" IsDiscount="N" IsRefundable="Y" Lockid="0"
    Modifyprogid="XMLMigrator" Modifyts="2019-05-28T20:42:50-04:00"
    Modifyuserid="SYSTEM" OrganizationCode="DEFAULT"/>
<ChargeCategory ChargeCategory="Personalization"
    ChargeCategoryKey="200206122335406737" ConsiderForProfitMargin="N"
    Createprogid="XMLMigrator" Createts="2019-05-28T20:42:50-04:00"
    Createuserid="SYSTEM" Description="Personalization"
    DocumentType="0005" IsBillable="Y" IsDiscount="N" IsRefundable="Y"
    Lockid="0" Modifyprogid="XMLMigrator"
    Modifyts="2019-05-28T20:42:50-04:00" Modifyuserid="SYSTEM" OrganizationCode="DEFAULT"/>
<ChargeCategory ChargeCategory="Discount"
    ChargeCategoryKey="200206122335406739" ConsiderForProfitMargin="N"
    Createprogid="XMLMigrator" Createts="2019-05-28T20:42:50-04:00"
    Createuserid="SYSTEM" Description="Discount" DocumentType="0005"
    IsBillable="Y" IsDiscount="Y" IsRefundable="Y" Lockid="0"
    Modifyprogid="XMLMigrator" Modifyts="2019-05-28T20:42:50-04:00"
    Modifyuserid="SYSTEM" OrganizationCode="DEFAULT"/>
<ChargeCategory ChargeCategory="Personalization"
    ChargeCategoryKey="2002087940966" ConsiderForProfitMargin="Y"
    Createprogid="XMLMigrator" Createts="2019-05-28T22:11:34-04:00"
    Createuserid="SYSTEM" Description="Personalization"
    DocumentType="0001" IsBillable="Y" IsDiscount="N" IsRefundable="N"
    Lockid="0" Modifyprogid="XMLMigrator"
    Modifyts="2019-05-28T22:11:34-04:00" Modifyuserid="SYSTEM" OrganizationCode="Aurora-Corp"/>
<ChargeCategory ChargeCategory="Shipping"
    ChargeCategoryKey="200271208489" ConsiderForProfitMargin="Y"
    Createprogid="XMLMigrator" Createts="2019-05-28T22:11:59-04:00"
    Createuserid="SYSTEM" Description="Shipping" DocumentType="0003"
    IsBillable="Y" IsDiscount="N" IsRefundable="Y" Lockid="0"
    Modifyprogid="XMLMigrator" Modifyts="2019-05-28T22:11:59-04:00"
    Modifyuserid="SYSTEM" OrganizationCode="Aurora"/>
<ChargeCategory ChargeCategory="Shipping"
    ChargeCategoryKey="200290023627" ConsiderForProfitMargin="Y"
    Createprogid="XMLMigrator" Createts="2019-05-28T22:11:35-04:00"
    Createuserid="SYSTEM" Description="Shipping" DocumentType="0015"
    IsBillable="Y" IsDiscount="N" IsRefundable="Y" Lockid="0"
    Modifyprogid="XMLMigrator" Modifyts="2019-05-28T22:11:35-04:00"
    Modifyuserid="SYSTEM" OrganizationCode="Aurora-Corp"/>
<ChargeCategory ChargeCategory="Shipping"
    ChargeCategoryKey="20030708142437508" ConsiderForProfitMargin="N"
    Createprogid="XMLMigrator" Createts="2019-05-28T20:42:50-04:00"
    Createuserid="SYSTEM" Description="Shipping" DocumentType="0006"
    IsBillable="Y" IsDiscount="N" IsRefundable="Y" Lockid="0"
    Modifyprogid="XMLMigrator" Modifyts="2019-05-28T20:42:50-04:00"
    Modifyuserid="SYSTEM" OrganizationCode="DEFAULT"/>
<ChargeCategory ChargeCategory="Handling"
    ChargeCategoryKey="20030708142437510" ConsiderForProfitMargin="N"
    Createprogid="XMLMigrator" Createts="2019-05-28T20:42:50-04:00"
    Createuserid="SYSTEM" Description="Handling" DocumentType="0006"
    IsBillable="Y" IsDiscount="N" IsRefundable="Y" Lockid="0"
    Modifyprogid="XMLMigrator" Modifyts="2019-05-28T20:42:50-04:00"
    Modifyuserid="SYSTEM" OrganizationCode="DEFAULT"/>
<ChargeCategory ChargeCategory="Personalization"
    ChargeCategoryKey="20030708142437512" ConsiderForProfitMargin="N"
    Createprogid="XMLMigrator" Createts="2019-05-28T20:42:50-04:00"
    Createuserid="SYSTEM" Description="Personalization"
    DocumentType="0006" IsBillable="Y" IsDiscount="N" IsRefundable="Y"
    Lockid="0" Modifyprogid="XMLMigrator"
    Modifyts="2019-05-28T20:42:50-04:00" Modifyuserid="SYSTEM" OrganizationCode="DEFAULT"/>
<ChargeCategory ChargeCategory="Discount"
    ChargeCategoryKey="20030708142437514" ConsiderForProfitMargin="N"
    Createprogid="XMLMigrator" Createts="2019-05-28T20:42:50-04:00"
    Createuserid="SYSTEM" Description="Discount" DocumentType="0006"
    IsBillable="Y" IsDiscount="Y" IsRefundable="Y" Lockid="0"
    Modifyprogid="XMLMigrator" Modifyts="2019-05-28T20:42:50-04:00"
    Modifyuserid="SYSTEM" OrganizationCode="DEFAULT"/>
<ChargeCategory ChargeCategory="Coupon" ChargeCategoryKey="200375568531"
    ConsiderForProfitMargin="Y" Createprogid="XMLMigrator"
    Createts="2019-05-28T22:11:35-04:00" Createuserid="SYSTEM"
    Description="Coupon" DocumentType="0015" IsBillable="Y"
    IsDiscount="Y" IsRefundable="Y" Lockid="0"
    Modifyprogid="XMLMigrator" Modifyts="2019-05-28T22:11:35-04:00"
    Modifyuserid="SYSTEM" OrganizationCode="Aurora-Corp"/>
<ChargeCategory ChargeCategory="CUSTOMER_APPEASEMENT"
    ChargeCategoryKey="200404728905" ConsiderForProfitMargin="Y"
    Createprogid="XMLMigrator" Createts="2019-05-28T22:11:58-04:00"
    Createuserid="SYSTEM" Description="Customer Appeasement"
    DocumentType="0001" IsBillable="Y" IsDiscount="Y" IsRefundable="Y"
    Lockid="0" Modifyprogid="XMLMigrator"
    Modifyts="2019-05-28T22:11:58-04:00" Modifyuserid="SYSTEM" OrganizationCode="Aurora"/>
<ChargeCategory ChargeCategory="ShippingDiscount"
    ChargeCategoryKey="20058889322" ConsiderForProfitMargin="Y"
    Createprogid="XMLMigrator" Createts="2019-05-28T22:11:35-04:00"
    Createuserid="SYSTEM" Description="Shipping Discount"
    DocumentType="0015" IsBillable="Y" IsDiscount="N" IsRefundable="Y"
    Lockid="0" Modifyprogid="XMLMigrator"
    Modifyts="2019-05-28T22:11:35-04:00" Modifyuserid="SYSTEM" OrganizationCode="Aurora-Corp"/>
<ChargeCategory ChargeCategory="Coupon" ChargeCategoryKey="200741620015"
    ConsiderForProfitMargin="Y" Createprogid="XMLMigrator"
    Createts="2019-05-28T22:11:58-04:00" Createuserid="SYSTEM"
    Description="Coupon" DocumentType="0001" IsBillable="Y"
    IsDiscount="Y" IsRefundable="Y" Lockid="0"
    Modifyprogid="XMLMigrator" Modifyts="2019-05-28T22:11:58-04:00"
    Modifyuserid="SYSTEM" OrganizationCode="Aurora"/>
<ChargeCategory ChargeCategory="PriceMatch"
    ChargeCategoryKey="201161236931" ConsiderForProfitMargin="Y"
    Createprogid="XMLMigrator" Createts="2019-05-28T22:11:35-04:00"
    Createuserid="SYSTEM" Description="Price Match" DocumentType="0015"
    IsBillable="Y" IsDiscount="Y" IsRefundable="Y" Lockid="0"
    Modifyprogid="XMLMigrator" Modifyts="2019-05-28T22:11:35-04:00"
    Modifyuserid="SYSTEM" OrganizationCode="Aurora-Corp"/>
<ChargeCategory ChargeCategory="Shipping"
    ChargeCategoryKey="20121818521" ConsiderForProfitMargin="Y"
    Createprogid="XMLMigrator" Createts="2019-05-28T22:11:58-04:00"
    Createuserid="SYSTEM" Description="Shipping" DocumentType="0001"
    IsBillable="Y" IsDiscount="N" IsRefundable="Y" Lockid="0"
    Modifyprogid="XMLMigrator" Modifyts="2019-05-28T22:11:58-04:00"
    Modifyuserid="SYSTEM" OrganizationCode="Aurora"/>
<ChargeCategory ChargeCategory="Coupon" ChargeCategoryKey="20127199566"
    ConsiderForProfitMargin="Y" Createprogid="XMLMigrator"
    Createts="2019-05-28T22:11:59-04:00" Createuserid="SYSTEM"
    Description="Coupon" DocumentType="0015" IsBillable="Y"
    IsDiscount="Y" IsRefundable="Y" Lockid="0"
    Modifyprogid="XMLMigrator" Modifyts="2019-05-28T22:11:59-04:00"
    Modifyuserid="SYSTEM" OrganizationCode="Aurora"/>
<ChargeCategory ChargeCategory="CUSTOMER_APPEASEMENT"
    ChargeCategoryKey="201277745012" ConsiderForProfitMargin="Y"
    Createprogid="XMLMigrator" Createts="2019-05-28T22:11:59-04:00"
    Createuserid="SYSTEM" Description="Customer Appeasement"
    DocumentType="0015" IsBillable="Y" IsDiscount="Y" IsRefundable="Y"
    Lockid="0" Modifyprogid="XMLMigrator"
    Modifyts="2019-05-28T22:11:59-04:00" Modifyuserid="SYSTEM" OrganizationCode="Aurora"/>
<ChargeCategory ChargeCategory="PriceMatch"
    ChargeCategoryKey="201804549927" ConsiderForProfitMargin="Y"
    Createprogid="XMLMigrator" Createts="2019-05-28T22:11:58-04:00"
    Createuserid="SYSTEM" Description="Price Match" DocumentType="0001"
    IsBillable="Y" IsDiscount="Y" IsRefundable="Y" Lockid="0"
    Modifyprogid="XMLMigrator" Modifyts="2019-05-28T22:11:58-04:00"
    Modifyuserid="SYSTEM" OrganizationCode="Aurora"/>
<ChargeCategory ChargeCategory="Shipping"
    ChargeCategoryKey="201833780438" ConsiderForProfitMargin="Y"
    Createprogid="XMLMigrator" Createts="2019-05-28T22:11:59-04:00"
    Createuserid="SYSTEM" Description="Shipping" DocumentType="0015"
    IsBillable="Y" IsDiscount="N" IsRefundable="Y" Lockid="0"
    Modifyprogid="XMLMigrator" Modifyts="2019-05-28T22:11:59-04:00"
    Modifyuserid="SYSTEM" OrganizationCode="Aurora"/>
<ChargeCategory ChargeCategory="Shipping"
    ChargeCategoryKey="201899954742" ConsiderForProfitMargin="Y"
    Createprogid="XMLMigrator" Createts="2019-05-28T22:11:34-04:00"
    Createuserid="SYSTEM" Description="Shipping" DocumentType="0003"
    IsBillable="Y" IsDiscount="N" IsRefundable="Y" Lockid="0"
    Modifyprogid="XMLMigrator" Modifyts="2019-05-28T22:11:34-04:00"
    Modifyuserid="SYSTEM" OrganizationCode="Aurora-Corp"/>
<ChargeCategory ChargeCategory="CUSTOMER_APPEASEMENT"
    ChargeCategoryKey="201925616467" ConsiderForProfitMargin="Y"
    Createprogid="XMLMigrator" Createts="2019-05-28T22:11:35-04:00"
    Createuserid="SYSTEM" Description="Customer Appeasement"
    DocumentType="0015" IsBillable="Y" IsDiscount="Y" IsRefundable="Y"
    Lockid="0" Modifyprogid="XMLMigrator"
    Modifyts="2019-05-28T22:11:35-04:00" Modifyuserid="SYSTEM" OrganizationCode="Aurora-Corp"/>
<ChargeCategory ChargeCategory="PriceMatch"
    ChargeCategoryKey="202027477796" ConsiderForProfitMargin="Y"
    Createprogid="XMLMigrator" Createts="2019-05-28T22:11:59-04:00"
    Createuserid="SYSTEM" Description="Price Match" DocumentType="0015"
    IsBillable="Y" IsDiscount="Y" IsRefundable="Y" Lockid="0"
    Modifyprogid="XMLMigrator" Modifyts="2019-05-28T22:11:59-04:00"
    Modifyuserid="SYSTEM" OrganizationCode="Aurora"/>
<ChargeCategory ChargeCategory="Handling"
    ChargeCategoryKey="20228285036" ConsiderForProfitMargin="Y"
    Createprogid="XMLMigrator" Createts="2019-05-28T22:11:35-04:00"
    Createuserid="SYSTEM" Description="Handling" DocumentType="0015"
    IsBillable="Y" IsDiscount="N" IsRefundable="N" Lockid="0"
    Modifyprogid="XMLMigrator" Modifyts="2019-05-28T22:11:35-04:00"
    Modifyuserid="SYSTEM" OrganizationCode="Aurora-Corp"/>
<ChargeCategory ChargeCategory="CUSTOMER_APPEASEMENT"
    ChargeCategoryKey="20243142550" ConsiderForProfitMargin="Y"
    Createprogid="XMLMigrator" Createts="2019-05-28T22:11:34-04:00"
    Createuserid="SYSTEM" Description="Customer Appeasement"
    DocumentType="0001" IsBillable="Y" IsDiscount="Y" IsRefundable="Y"
    Lockid="0" Modifyprogid="XMLMigrator"
    Modifyts="2019-05-28T22:11:34-04:00" Modifyuserid="SYSTEM" OrganizationCode="Aurora-Corp"/>
<ChargeCategory ChargeCategory="Handling"
    ChargeCategoryKey="20247100174" ConsiderForProfitMargin="Y"
    Createprogid="XMLMigrator" Createts="2019-05-28T22:11:58-04:00"
    Createuserid="SYSTEM" Description="Handling" DocumentType="0003"
    IsBillable="Y" IsDiscount="N" IsRefundable="N" Lockid="0"
    Modifyprogid="XMLMigrator" Modifyts="2019-05-28T22:11:58-04:00"
    Modifyuserid="SYSTEM" OrganizationCode="Aurora"/>
<ChargeCategory ChargeCategory="Personalization"
    ChargeCategoryKey="20270956505" ConsiderForProfitMargin="Y"
    Createprogid="XMLMigrator" Createts="2019-05-28T22:11:58-04:00"
    Createuserid="SYSTEM" Description="Personalization"
    DocumentType="0001" IsBillable="Y" IsDiscount="N" IsRefundable="N"
    Lockid="0" Modifyprogid="XMLMigrator"
    Modifyts="2019-05-28T22:11:58-04:00" Modifyuserid="SYSTEM" OrganizationCode="Aurora"/>
<ChargeCategory ChargeCategory="Personalization"
    ChargeCategoryKey="20392155644" ConsiderForProfitMargin="Y"
    Createprogid="XMLMigrator" Createts="2019-05-28T22:11:59-04:00"
    Createuserid="SYSTEM" Description="Personalization"
    DocumentType="0015" IsBillable="Y" IsDiscount="N" IsRefundable="N"
    Lockid="0" Modifyprogid="XMLMigrator"
    Modifyts="2019-05-28T22:11:59-04:00" Modifyuserid="SYSTEM" OrganizationCode="Aurora"/>
<ChargeCategory ChargeCategory="ShippingDiscount"
    ChargeCategoryKey="20478904665" ConsiderForProfitMargin="Y"
    Createprogid="XMLMigrator" Createts="2019-05-28T22:11:34-04:00"
    Createuserid="SYSTEM" Description="Shipping Discount"
    DocumentType="0001" IsBillable="Y" IsDiscount="N" IsRefundable="Y"
    Lockid="0" Modifyprogid="XMLMigrator"
    Modifyts="2019-05-28T22:11:34-04:00" Modifyuserid="SYSTEM" OrganizationCode="Aurora-Corp"/>
<ChargeCategory ChargeCategory="Discount"
    ChargeCategoryKey="20499396296" ConsiderForProfitMargin="Y"
    Createprogid="XMLMigrator" Createts="2019-05-28T22:11:35-04:00"
    Createuserid="SYSTEM" Description="Discount" DocumentType="0015"
    IsBillable="Y" IsDiscount="Y" IsRefundable="Y" Lockid="0"
    Modifyprogid="XMLMigrator" Modifyts="2019-05-28T22:11:35-04:00"
    Modifyuserid="SYSTEM" OrganizationCode="Aurora-Corp"/>
<ChargeCategory ChargeCategory="Discount"
    ChargeCategoryKey="20518211434" ConsiderForProfitMargin="Y"
    Createprogid="XMLMigrator" Createts="2019-05-28T22:11:58-04:00"
    Createuserid="SYSTEM" Description="Discount" DocumentType="0003"
    IsBillable="Y" IsDiscount="Y" IsRefundable="Y" Lockid="0"
    Modifyprogid="XMLMigrator" Modifyts="2019-05-28T22:11:58-04:00"
    Modifyuserid="SYSTEM" OrganizationCode="Aurora"/>
<ChargeCategory ChargeCategory="ShippingDiscount"
    ChargeCategoryKey="2052488247" ConsiderForProfitMargin="Y"
    Createprogid="XMLMigrator" Createts="2019-05-28T22:11:59-04:00"
    Createuserid="SYSTEM" Description="Shipping Discount"
    DocumentType="0015" IsBillable="Y" IsDiscount="N" IsRefundable="Y"
    Lockid="0" Modifyprogid="XMLMigrator"
    Modifyts="2019-05-28T22:11:59-04:00" Modifyuserid="SYSTEM" OrganizationCode="Aurora"/>
<ChargeCategory ChargeCategory="ShippingDiscount"
    ChargeCategoryKey="20590282234" ConsiderForProfitMargin="Y"
    Createprogid="XMLMigrator" Createts="2019-05-28T22:11:58-04:00"
    Createuserid="SYSTEM" Description="Shipping Discount"
    DocumentType="0001" IsBillable="Y" IsDiscount="N" IsRefundable="Y"
    Lockid="0" Modifyprogid="XMLMigrator"
    Modifyts="2019-05-28T22:11:58-04:00" Modifyuserid="SYSTEM" OrganizationCode="Aurora"/>
<ChargeCategory ChargeCategory="Personalization"
    ChargeCategoryKey="20618678428" ConsiderForProfitMargin="Y"
    Createprogid="XMLMigrator" Createts="2019-05-28T22:11:34-04:00"
    Createuserid="SYSTEM" Description="Personalization"
    DocumentType="0003" IsBillable="Y" IsDiscount="N" IsRefundable="N"
    Lockid="0" Modifyprogid="XMLMigrator"
    Modifyts="2019-05-28T22:11:34-04:00" Modifyuserid="SYSTEM" OrganizationCode="Aurora-Corp"/>
<ChargeCategory ChargeCategory="Handling"
    ChargeCategoryKey="20640127184" ConsiderForProfitMargin="Y"
    Createprogid="XMLMigrator" Createts="2019-05-28T22:11:58-04:00"
    Createuserid="SYSTEM" Description="Handling" DocumentType="0001"
    IsBillable="Y" IsDiscount="N" IsRefundable="N" Lockid="0"
    Modifyprogid="XMLMigrator" Modifyts="2019-05-28T22:11:58-04:00"
    Modifyuserid="SYSTEM" OrganizationCode="Aurora"/>
<ChargeCategory ChargeCategory="Discount"
    ChargeCategoryKey="20911238444" ConsiderForProfitMargin="Y"
    Createprogid="XMLMigrator" Createts="2019-05-28T22:11:58-04:00"
    Createuserid="SYSTEM" Description="Discount" DocumentType="0001"
    IsBillable="Y" IsDiscount="Y" IsRefundable="Y" Lockid="0"
    Modifyprogid="XMLMigrator" Modifyts="2019-05-28T22:11:58-04:00"
    Modifyuserid="SYSTEM" OrganizationCode="Aurora"/>
<ChargeCategory ChargeCategory="PriceMatch"
    ChargeCategoryKey="20938309062" ConsiderForProfitMargin="Y"
    Createprogid="XMLMigrator" Createts="2019-05-28T22:11:34-04:00"
    Createuserid="SYSTEM" Description="Price Match" DocumentType="0001"
    IsBillable="Y" IsDiscount="Y" IsRefundable="Y" Lockid="0"
    Modifyprogid="XMLMigrator" Modifyts="2019-05-28T22:11:34-04:00"
    Modifyuserid="SYSTEM" OrganizationCode="Aurora-Corp"/>
<ChargeCategory ChargeCategory="Shipping"
    ChargeCategoryKey="DEFAULT_CHARGE_KEY_01"
    ConsiderForProfitMargin="N" Createprogid="XMLMigrator"
    Createts="2019-05-28T20:42:50-04:00" Createuserid="SYSTEM"
    Description="Shipping" DocumentType="0001" IsBillable="Y"
    IsDiscount="N" IsRefundable="Y" Lockid="0"
    Modifyprogid="XMLMigrator" Modifyts="2019-05-28T20:42:50-04:00"
    Modifyuserid="SYSTEM" OrganizationCode="DEFAULT"/>
<ChargeCategory ChargeCategory="Handling"
    ChargeCategoryKey="DEFAULT_CHARGE_KEY_02"
    ConsiderForProfitMargin="N" Createprogid="XMLMigrator"
    Createts="2019-05-28T20:42:50-04:00" Createuserid="SYSTEM"
    Description="Handling" DocumentType="0001" IsBillable="Y"
    IsDiscount="N" IsRefundable="Y" Lockid="0"
    Modifyprogid="XMLMigrator" Modifyts="2019-05-28T20:42:50-04:00"
    Modifyuserid="SYSTEM" OrganizationCode="DEFAULT"/>
<ChargeCategory ChargeCategory="Personalization"
    ChargeCategoryKey="DEFAULT_CHARGE_KEY_03"
    ConsiderForProfitMargin="N" Createprogid="XMLMigrator"
    Createts="2019-05-28T20:42:50-04:00" Createuserid="SYSTEM"
    Description="Personalization" DocumentType="0001" IsBillable="Y"
    IsDiscount="N" IsRefundable="Y" Lockid="0"
    Modifyprogid="XMLMigrator" Modifyts="2019-05-28T20:42:50-04:00"
    Modifyuserid="SYSTEM" OrganizationCode="DEFAULT"/>
<ChargeCategory ChargeCategory="Discount"
    ChargeCategoryKey="DEFAULT_CHARGE_KEY_04"
    ConsiderForProfitMargin="N" Createprogid="XMLMigrator"
    Createts="2019-05-28T20:42:50-04:00" Createuserid="SYSTEM"
    Description="Discount" DocumentType="0001" IsBillable="Y"
    IsDiscount="Y" IsRefundable="Y" Lockid="0"
    Modifyprogid="XMLMigrator" Modifyts="2019-05-28T20:42:50-04:00"
    Modifyuserid="SYSTEM" OrganizationCode="DEFAULT"/>
<ChargeCategory ChargeCategory="Shipping"
    ChargeCategoryKey="DEFAULT_CHARGE_KEY_21"
    ConsiderForProfitMargin="N" Createprogid="XMLMigrator"
    Createts="2019-05-28T20:42:50-04:00" Createuserid="SYSTEM"
    Description="Shipping" DocumentType="0002" IsBillable="Y"
    IsDiscount="N" IsRefundable="Y" Lockid="0"
    Modifyprogid="XMLMigrator" Modifyts="2019-05-28T20:42:50-04:00"
    Modifyuserid="SYSTEM" OrganizationCode="DEFAULT"/>
<ChargeCategory ChargeCategory="Handling"
    ChargeCategoryKey="DEFAULT_CHARGE_KEY_22"
    ConsiderForProfitMargin="N" Createprogid="XMLMigrator"
    Createts="2019-05-28T20:42:50-04:00" Createuserid="SYSTEM"
    Description="Handling" DocumentType="0002" IsBillable="Y"
    IsDiscount="N" IsRefundable="Y" Lockid="0"
    Modifyprogid="XMLMigrator" Modifyts="2019-05-28T20:42:50-04:00"
    Modifyuserid="SYSTEM" OrganizationCode="DEFAULT"/>
<ChargeCategory ChargeCategory="Personalization"
    ChargeCategoryKey="DEFAULT_CHARGE_KEY_23"
    ConsiderForProfitMargin="N" Createprogid="XMLMigrator"
    Createts="2019-05-28T20:42:50-04:00" Createuserid="SYSTEM"
    Description="Personalization" DocumentType="0002" IsBillable="Y"
    IsDiscount="N" IsRefundable="Y" Lockid="0"
    Modifyprogid="XMLMigrator" Modifyts="2019-05-28T20:42:50-04:00"
    Modifyuserid="SYSTEM" OrganizationCode="DEFAULT"/>
<ChargeCategory ChargeCategory="Discount"
    ChargeCategoryKey="DEFAULT_CHARGE_KEY_24"
    ConsiderForProfitMargin="N" Createprogid="XMLMigrator"
    Createts="2019-05-28T20:42:50-04:00" Createuserid="SYSTEM"
    Description="Discount" DocumentType="0002" IsBillable="Y"
    IsDiscount="Y" IsRefundable="Y" Lockid="0"
    Modifyprogid="XMLMigrator" Modifyts="2019-05-28T20:42:50-04:00"
    Modifyuserid="SYSTEM" OrganizationCode="DEFAULT"/>
<ChargeCategory ChargeCategory="Shipping"
    ChargeCategoryKey="DEFAULT_CHARGE_KEY_L1"
    ConsiderForProfitMargin="N" Createprogid="XMLMigrator"
    Createts="2019-05-28T20:42:50-04:00" Createuserid="SYSTEM"
    Description="Shipping" DocumentType="1001" IsBillable="Y"
    IsDiscount="N" IsRefundable="Y" Lockid="0"
    Modifyprogid="XMLMigrator" Modifyts="2019-05-28T20:42:50-04:00"
    Modifyuserid="SYSTEM" OrganizationCode="DEFAULT"/>
<ChargeCategory ChargeCategory="Handling"
    ChargeCategoryKey="DEFAULT_CHARGE_KEY_L2"
    ConsiderForProfitMargin="N" Createprogid="XMLMigrator"
    Createts="2019-05-28T20:42:50-04:00" Createuserid="SYSTEM"
    Description="Handling" DocumentType="1001" IsBillable="Y"
    IsDiscount="N" IsRefundable="Y" Lockid="0"
    Modifyprogid="XMLMigrator" Modifyts="2019-05-28T20:42:50-04:00"
    Modifyuserid="SYSTEM" OrganizationCode="DEFAULT"/>
<ChargeCategory ChargeCategory="Personalization"
    ChargeCategoryKey="DEFAULT_CHARGE_KEY_L3"
    ConsiderForProfitMargin="N" Createprogid="XMLMigrator"
    Createts="2019-05-28T20:42:50-04:00" Createuserid="SYSTEM"
    Description="Personalization" DocumentType="1001" IsBillable="Y"
    IsDiscount="N" IsRefundable="Y" Lockid="0"
    Modifyprogid="XMLMigrator" Modifyts="2019-05-28T20:42:50-04:00"
    Modifyuserid="SYSTEM" OrganizationCode="DEFAULT"/>
<ChargeCategory ChargeCategory="Discount"
    ChargeCategoryKey="DEFAULT_CHARGE_KEY_L4"
    ConsiderForProfitMargin="N" Createprogid="XMLMigrator"
    Createts="2019-05-28T20:42:50-04:00" Createuserid="SYSTEM"
    Description="Discount" DocumentType="1001" IsBillable="Y"
    IsDiscount="Y" IsRefundable="Y" Lockid="0"
    Modifyprogid="XMLMigrator" Modifyts="2019-05-28T20:42:50-04:00"
    Modifyuserid="SYSTEM" OrganizationCode="DEFAULT"/>
<ChargeCategory ChargeCategory="Discount"
    ChargeCategoryKey="Discount0007" ConsiderForProfitMargin="N"
    Createprogid="XMLMigrator" Createts="2019-05-28T20:42:50-04:00"
    Createuserid="SYSTEM" Description="Discount" DocumentType="0007"
    IsBillable="Y" IsDiscount="Y" IsRefundable="Y" Lockid="0"
    Modifyprogid="XMLMigrator" Modifyts="2019-05-28T20:42:50-04:00"
    Modifyuserid="SYSTEM" OrganizationCode="DEFAULT"/>
<ChargeCategory ChargeCategory="Discount"
    ChargeCategoryKey="Discount0015" ConsiderForProfitMargin="Y"
    Createprogid="XMLMigrator" Createts="2019-05-28T20:42:50-04:00"
    Createuserid="SYSTEM" Description="Discount" DocumentType="0015"
    IsBillable="Y" IsDiscount="Y" IsRefundable="Y" Lockid="0"
    Modifyprogid="XMLMigrator" Modifyts="2019-05-28T20:42:50-04:00"
    Modifyuserid="SYSTEM" OrganizationCode="DEFAULT"/>
<ChargeCategory ChargeCategory="Handling"
    ChargeCategoryKey="Handling0007" ConsiderForProfitMargin="N"
    Createprogid="XMLMigrator" Createts="2019-05-28T20:42:50-04:00"
    Createuserid="SYSTEM" Description="Handling" DocumentType="0007"
    IsBillable="Y" IsDiscount="N" IsRefundable="Y" Lockid="0"
    Modifyprogid="XMLMigrator" Modifyts="2019-05-28T20:42:50-04:00"
    Modifyuserid="SYSTEM" OrganizationCode="DEFAULT"/>
<ChargeCategory ChargeCategory="Handling"
    ChargeCategoryKey="Handling0015" ConsiderForProfitMargin="N"
    Createprogid="XMLMigrator" Createts="2019-05-28T20:42:50-04:00"
    Createuserid="SYSTEM" Description="Handling" DocumentType="0015"
    IsBillable="Y" IsDiscount="N" IsRefundable="Y" Lockid="0"
    Modifyprogid="XMLMigrator" Modifyts="2019-05-28T20:42:50-04:00"
    Modifyuserid="SYSTEM" OrganizationCode="DEFAULT"/>
<ChargeCategory ChargeCategory="Personalization"
    ChargeCategoryKey="Personalization0007" ConsiderForProfitMargin="N"
    Createprogid="XMLMigrator" Createts="2019-05-28T20:42:50-04:00"
    Createuserid="SYSTEM" Description="Personalization"
    DocumentType="0007" IsBillable="Y" IsDiscount="N" IsRefundable="Y"
    Lockid="0" Modifyprogid="XMLMigrator"
    Modifyts="2019-05-28T20:42:50-04:00" Modifyuserid="SYSTEM" OrganizationCode="DEFAULT"/>
<ChargeCategory ChargeCategory="Personalization"
    ChargeCategoryKey="Personalization0015" ConsiderForProfitMargin="N"
    Createprogid="XMLMigrator" Createts="2019-05-28T20:42:50-04:00"
    Createuserid="SYSTEM" Description="Personalization"
    DocumentType="0015" IsBillable="Y" IsDiscount="N" IsRefundable="Y"
    Lockid="0" Modifyprogid="XMLMigrator"
    Modifyts="2019-05-28T20:42:50-04:00" Modifyuserid="SYSTEM" OrganizationCode="DEFAULT"/>
<ChargeCategory ChargeCategory="Shipping"
    ChargeCategoryKey="Shipping0007" ConsiderForProfitMargin="N"
    Createprogid="XMLMigrator" Createts="2019-05-28T20:42:50-04:00"
    Createuserid="SYSTEM" Description="Shipping" DocumentType="0007"
    IsBillable="Y" IsDiscount="N" IsRefundable="Y" Lockid="0"
    Modifyprogid="XMLMigrator" Modifyts="2019-05-28T20:42:50-04:00"
    Modifyuserid="SYSTEM" OrganizationCode="DEFAULT"/>
<ChargeCategory ChargeCategory="Shipping"
    ChargeCategoryKey="Shippint0015" ConsiderForProfitMargin="N"
    Createprogid="XMLMigrator" Createts="2019-05-28T20:42:50-04:00"
    Createuserid="SYSTEM" Description="Shipping" DocumentType="0015"
    IsBillable="Y" IsDiscount="N" IsRefundable="Y" Lockid="0"
    Modifyprogid="XMLMigrator" Modifyts="2019-05-28T20:42:50-04:00"
    Modifyuserid="SYSTEM" OrganizationCode="DEFAULT"/>
</YFS_CHARGE_CATEGORYList>